{
  "hash": "7f193d5c",
  "configHash": "8cc000fa",
  "lockfileHash": "b72c73b8",
  "browserHash": "56a6d0a8",
  "optimized": {
    "react": {
      "src": "../../node_modules/react/index.js",
      "file": "react.js",
      "fileHash": "ae53f195",
      "needsInterop": true
    },
    "react-dom/client": {
      "src": "../../node_modules/react-dom/client.js",
      "file": "react-dom_client.js",
      "fileHash": "d5f8d574",
      "needsInterop": true
    }
  },
  "chunks": {
    "chunk-B2WE2YPZ": {
      "file": "chunk-B2WE2YPZ.js"
    }
  }
}